jsonschema_models/__init__.py
jsonschema_models/models.py
jsonschema_models/py.typed
jsonschema_models-1.2.1.dist-info/METADATA
jsonschema_models-1.2.1.dist-info/WHEEL
jsonschema_models-1.2.1.dist-info/licenses/LICENSE
jsonschema_models-1.2.1.dist-info/RECORD
