Metadata-Version: 2.4
Name: jsonschema-models
Version: 1.2.1
Summary: Pydantic models for representing JSON Schema objects
Project-URL: Homepage, https://github.com/gmr/jsonschema-models
Project-URL: Bug Tracker, https://github.com/gmr/jsonschema-models/issues
Author-email: "Gavin M. Roy" <gavinr@aweber.com>
License: BSD 3-Clause License
License-File: LICENSE
Classifier: Development Status :: 3 - Alpha
Classifier: Intended Audience :: Developers
Classifier: License :: OSI Approved :: BSD License
Classifier: Programming Language :: Python :: 3
Classifier: Programming Language :: Python :: 3.12
Classifier: Programming Language :: Python :: 3.13
Requires-Python: >=3.12
Requires-Dist: pydantic
Provides-Extra: dev
Requires-Dist: build; extra == 'dev'
Requires-Dist: mypy; extra == 'dev'
Requires-Dist: pre-commit; extra == 'dev'
Requires-Dist: pytest; extra == 'dev'
Requires-Dist: pytest-cov; extra == 'dev'
Requires-Dist: ruff; extra == 'dev'
